Metadata-Version: 2.1
Name: boredmoments
Version: 0.1
Summary: commandline games
Home-page: https://github.com/Daniel-Kenan/Minesweeper
Author: auth
Author-email: sdanielkenan@email.com
License: MIT
Platform: UNKNOWN
License-File: LICENSE
